[{"line":2,"elements":[{"line":4,"name":"","description":"","type":"background","keyword":"Background","steps":[{"result":{"duration":9184365000,"status":"passed"},"line":5,"name":"User should be on the login page","match":{"location":"com.krafttech.step_definitions.Login_stepDefs.user_should_be_on_the_login_page()"},"keyword":"Given "}]},{"start_timestamp":"2022-12-14T19:07:35.138Z","before":[{"result":{"duration":1999100,"status":"passed"},"match":{"location":"com.krafttech.step_definitions.Hooks.setUp()"}}],"line":13,"name":"Login as Jhon Nash","description":"","id":"krafttech-log-in-test;login-as-jhon-nash","after":[{"result":{"duration":542497500,"status":"passed"},"match":{"location":"com.krafttech.step_definitions.Hooks.tearDown(io.cucumber.java.Scenario)"}}],"type":"scenario","keyword":"Scenario","steps":[{"result":{"status":"passed"},"line":14,"name":"The user enters Jhon Nash credentials","match":{"location":"com.krafttech.step_definitions.Login_stepDefs.the_user_enters_jhon_nash_credentials()"},"keyword":"When "},{"result":{"status":"passed"},"line":15,"name":"The user should be able to login","match":{"location":"com.krafttech.step_definitions.Login_stepDefs.the_user_should_be_able_to_login()"},"keyword":"Then "}],"tags":[{"name":"@login"},{"name":"@rerun"}]},{"line":4,"name":"","description":"","type":"background","keyword":"Background","steps":[{"result":{"duration":6542061800,"status":"passed"},"line":5,"name":"User should be on the login page","match":{"location":"com.krafttech.step_definitions.Login_stepDefs.user_should_be_on_the_login_page()"},"keyword":"Given "}]},{"start_timestamp":"2022-12-14T19:07:44.895Z","before":[{"result":{"duration":999800,"status":"passed"},"match":{"location":"com.krafttech.step_definitions.Hooks.setUp()"}}],"line":18,"name":"Login as Emel","description":"","id":"krafttech-log-in-test;login-as-emel","after":[{"result":{"duration":127919600,"status":"passed"},"match":{"location":"com.krafttech.step_definitions.Hooks.tearDown(io.cucumber.java.Scenario)"}}],"type":"scenario","keyword":"Scenario","steps":[{"result":{"status":"passed"},"line":19,"name":"The user enters Emel credentials","match":{"location":"com.krafttech.step_definitions.Login_stepDefs.the_user_enters_emel_credentials()"},"keyword":"When "},{"result":{"status":"passed"},"line":20,"name":"The user should be able to login","match":{"location":"com.krafttech.step_definitions.Login_stepDefs.the_user_should_be_able_to_login()"},"keyword":"Then "}],"tags":[{"name":"@login"},{"name":"@rerun"}]}],"name":"Krafttech Log in Test","description":"","id":"krafttech-log-in-test","keyword":"Feature","uri":"file:src/test/resources/features/Login.feature","tags":[{"name":"@login","type":"Tag","location":{"line":1,"column":1}}]},{"line":1,"elements":[{"start_timestamp":"2022-12-14T19:07:35.141Z","before":[{"result":{"duration":1999100,"status":"passed"},"match":{"location":"com.krafttech.step_definitions.Hooks.setUp()"}}],"line":10,"name":"Second user","description":"","id":"account-type;second-user","after":[{"result":{"duration":524273700,"status":"passed"},"match":{"location":"com.krafttech.step_definitions.Hooks.tearDown(io.cucumber.java.Scenario)"}}],"type":"scenario","keyword":"Scenario","steps":[{"result":{"duration":11295533900,"status":"passed"},"line":11,"name":"User should be on the login page","match":{"location":"com.krafttech.step_definitions.Login_stepDefs.user_should_be_on_the_login_page()"},"keyword":"Given "},{"result":{"duration":5730350200,"status":"passed"},"line":12,"name":"User should input \"eddiem@kraft.com\" and \"eddiem12\"","match":{"arguments":[{"val":"\"eddiem@kraft.com\"","offset":18},{"val":"\"eddiem12\"","offset":41}],"location":"com.krafttech.step_definitions.Login_stepDefs.userShouldInputAnd(java.lang.String,java.lang.String)"},"keyword":"When "},{"result":{"duration":93943000,"status":"passed"},"line":13,"name":"The user name should be \"Eddie Murphy\"","match":{"arguments":[{"val":"\"Eddie Murphy\"","offset":24}],"location":"com.krafttech.step_definitions.Dashboard_Step_Defs.the_user_name_should_be(java.lang.String)"},"keyword":"Then "}],"tags":[{"name":"@rerun"}]},{"start_timestamp":"2022-12-14T19:07:52.808Z","before":[{"result":{"status":"passed"},"match":{"location":"com.krafttech.step_definitions.Hooks.setUp()"}}],"line":16,"name":"Third user","description":"","id":"account-type;third-user","after":[{"result":{"duration":136353200,"status":"passed"},"match":{"location":"com.krafttech.step_definitions.Hooks.tearDown(io.cucumber.java.Scenario)"}}],"type":"scenario","keyword":"Scenario","steps":[{"result":{"duration":7828012400,"status":"passed"},"line":17,"name":"User should be on the login page","match":{"location":"com.krafttech.step_definitions.Login_stepDefs.user_should_be_on_the_login_page()"},"keyword":"Given "},{"result":{"duration":3199809800,"status":"passed"},"line":18,"name":"User should input \"morganfreeman@kraft.com\" and \"mfreeman\"","match":{"arguments":[{"val":"\"morganfreeman@kraft.com\"","offset":18},{"val":"\"mfreeman\"","offset":48}],"location":"com.krafttech.step_definitions.Login_stepDefs.userShouldInputAnd(java.lang.String,java.lang.String)"},"keyword":"When "},{"result":{"duration":62832900,"status":"passed"},"line":19,"name":"The user name should be \"Morgan Freeman\"","match":{"arguments":[{"val":"\"Morgan Freeman\"","offset":24}],"location":"com.krafttech.step_definitions.Dashboard_Step_Defs.the_user_name_should_be(java.lang.String)"},"keyword":"Then "}],"tags":[{"name":"@rerun"}]}],"name":"Account Type","description":"","id":"account-type","keyword":"Feature","uri":"file:src/test/resources/features/accountType.feature","tags":[]},{"line":2,"elements":[{"start_timestamp":"2022-12-14T19:07:35.139Z","before":[{"result":{"duration":1999100,"status":"passed"},"match":{"location":"com.krafttech.step_definitions.Hooks.setUp()"}}],"line":12,"name":"Eddie Murphy navigates to Developers menu","description":"","id":"navigate-to-menu-with-parameter;eddie-murphy-navigates-to-developers-menu","after":[{"result":{"duration":422991900,"status":"passed"},"match":{"location":"com.krafttech.step_definitions.Hooks.tearDown(io.cucumber.java.Scenario)"}}],"type":"scenario","keyword":"Scenario","steps":[{"result":{"duration":9909297300,"status":"passed"},"line":13,"name":"User should be on the login page","match":{"location":"com.krafttech.step_definitions.Login_stepDefs.user_should_be_on_the_login_page()"},"keyword":"Given "},{"result":{"duration":3097581800,"status":"passed"},"line":14,"name":"User should input \"eddiem@kraft.com\" and \"eddiem12\"","match":{"arguments":[{"val":"\"eddiem@kraft.com\"","offset":18},{"val":"\"eddiem12\"","offset":41}],"location":"com.krafttech.step_definitions.Login_stepDefs.userShouldInputAnd(java.lang.String,java.lang.String)"},"keyword":"When "},{"result":{"duration":89843900,"status":"passed"},"line":15,"name":"The user name should be \"Eddie Murphy\"","match":{"arguments":[{"val":"\"Eddie Murphy\"","offset":24}],"location":"com.krafttech.step_definitions.Dashboard_Step_Defs.the_user_name_should_be(java.lang.String)"},"keyword":"Then "},{"result":{"duration":1605914200,"status":"passed"},"line":16,"name":"The user navigates to \"Developers\" menu","match":{"arguments":[{"val":"\"Developers\"","offset":22}],"location":"com.krafttech.step_definitions.Dashboard_Step_Defs.the_user_navigates_to_menu(java.lang.String)"},"keyword":"When "},{"result":{"duration":1056353200,"status":"passed"},"line":17,"name":"The user should be able to see home name as \"Developers\"","match":{"arguments":[{"val":"\"Developers\"","offset":44}],"location":"com.krafttech.step_definitions.Dashboard_Step_Defs.the_user_should_be_able_to_see_home_name_as(java.lang.String)"},"keyword":"Then "}],"tags":[{"name":"@rerun"}]},{"start_timestamp":"2022-12-14T19:07:51.342Z","before":[{"result":{"duration":1000500,"status":"passed"},"match":{"location":"com.krafttech.step_definitions.Hooks.setUp()"}}],"line":20,"name":"Morgan Freeman navigates to Dashboard menu","description":"","id":"navigate-to-menu-with-parameter;morgan-freeman-navigates-to-dashboard-menu","after":[{"result":{"duration":128915900,"status":"passed"},"match":{"location":"com.krafttech.step_definitions.Hooks.tearDown(io.cucumber.java.Scenario)"}}],"type":"scenario","keyword":"Scenario","steps":[{"result":{"duration":7528170400,"status":"passed"},"line":21,"name":"User should be on the login page","match":{"location":"com.krafttech.step_definitions.Login_stepDefs.user_should_be_on_the_login_page()"},"keyword":"Given "},{"result":{"duration":3094607800,"status":"passed"},"line":22,"name":"User should input \"morganfreeman@kraft.com\" and \"mfreeman\"","match":{"arguments":[{"val":"\"morganfreeman@kraft.com\"","offset":18},{"val":"\"mfreeman\"","offset":48}],"location":"com.krafttech.step_definitions.Login_stepDefs.userShouldInputAnd(java.lang.String,java.lang.String)"},"keyword":"When "},{"result":{"duration":62171900,"status":"passed"},"line":23,"name":"The user name should be \"Morgan Freeman\"","match":{"arguments":[{"val":"\"Morgan Freeman\"","offset":24}],"location":"com.krafttech.step_definitions.Dashboard_Step_Defs.the_user_name_should_be(java.lang.String)"},"keyword":"Then "},{"result":{"duration":180527400,"status":"passed"},"line":24,"name":"The user navigates to \"Dashboard\" menu","match":{"arguments":[{"val":"\"Dashboard\"","offset":22}],"location":"com.krafttech.step_definitions.Dashboard_Step_Defs.the_user_navigates_to_menu(java.lang.String)"},"keyword":"When "},{"result":{"duration":1081817400,"status":"passed"},"line":25,"name":"The user should be able to see home name as \"Dashboard\"","match":{"arguments":[{"val":"\"Dashboard\"","offset":44}],"location":"com.krafttech.step_definitions.Dashboard_Step_Defs.the_user_should_be_able_to_see_home_name_as(java.lang.String)"},"keyword":"Then "}],"tags":[{"name":"@rerun"}]}],"name":"Navigate to menu with parameter","description":"","id":"navigate-to-menu-with-parameter","keyword":"Feature","uri":"file:src/test/resources/features/navigatesMenuWithParameter.feature","tags":[]}]